ipc_purepy/__init__.py
ipc_purepy/example.py
ipc_purepy/ipc.py
ipc_purepy/serializer.py
ipc_purepy-0.1.0.dist-info/LICENSE
ipc_purepy-0.1.0.dist-info/METADATA
ipc_purepy-0.1.0.dist-info/WHEEL
ipc_purepy-0.1.0.dist-info/top_level.txt
ipc_purepy-0.1.0.dist-info/RECORD
