Metadata-Version: 2.1
Name: ipc-purepy
Version: 0.1.0
Summary: Allow sent core Python objects between two likely independent Python processes using UNIX sockets.
Author-email: Michel Novus <michelnovus@gmail.com>
License: MIT License
Project-URL: Repository, https://github.com/michelnovus/ipc-purepy
Keywords: unix socket,ipc,process communication,simple,python primitives
Classifier: Programming Language :: Python :: 3
Classifier: License :: OSI Approved :: MIT License
Classifier: Intended Audience :: Developers
Classifier: Operating System :: POSIX :: Linux
Requires-Python: >=3.11
License-File: LICENSE
